comptes/__init__.py
comptes/admin.py
comptes/apps.py
comptes/forms.py
comptes/migrations/0001_initial.py
comptes/migrations/0002_auto_20150517_2022.py
comptes/migrations/0003_ordre.py
comptes/migrations/0004_auto_20150921_1254.py
comptes/migrations/0005_add_date_time_fields.py
comptes/migrations/0006_moment_to_date_time.py
comptes/migrations/0007_suppression_moment.py
comptes/migrations/0008_add_date_time_fields_again.py
comptes/migrations/0009_moment_to_date_time_again.py
comptes/migrations/0010_suppression_moment_again.py
comptes/migrations/0011_scribe.py
comptes/migrations/0012_cree_modifie.py
comptes/migrations/0013_verbose_name.py
comptes/migrations/0014_auto_20180106_2054.py
comptes/migrations/0015_auto_20180106_2055.py
comptes/migrations/0016_remove_occasion_nom.py
comptes/migrations/0017_auto_20180106_2110.py
comptes/migrations/0018_auto_20180106_2111.py
comptes/migrations/0019_auto_20180106_2130.py
comptes/migrations/0020_auto_20180106_2130.py
comptes/migrations/0021_auto_20180106_2144.py
comptes/migrations/__init__.py
comptes/models.py
comptes/py.typed
comptes/templates/comptes/dette_form.html
comptes/templates/comptes/mail_dette.md
comptes/templates/comptes/mail_remboursement.md
comptes/templates/comptes/occasion_detail.html
comptes/templates/comptes/occasion_list.html
comptes/urls.py
comptes/views.py
comptes-2.0.2.dist-info/LICENSE
comptes-2.0.2.dist-info/WHEEL
comptes-2.0.2.dist-info/METADATA
comptes-2.0.2.dist-info/RECORD
