Metadata-Version: 2.1
Name: comptes
Version: 2.0.2
Summary: Gestion des comptes
License: BSD-2-Clause
Author: Guilhem Saurel
Author-email: guilhem.saurel@laas.fr
Requires-Python: >=3.8,<4.0
Classifier: License :: OSI Approved :: BSD License
Classifier: Programming Language :: Python :: 3
Classifier: Programming Language :: Python :: 3.10
Classifier: Programming Language :: Python :: 3.8
Classifier: Programming Language :: Python :: 3.9
Requires-Dist: dmdm (>=1.4.5,<2.0.0)
Requires-Dist: ndh (>=5.1.2,<6.0.0)
